apiverve_colorconverter/__init__.py
apiverve_colorconverter/apiClient.py
apiverve_colorconverter/exceptions.py
apiverve_colorconverter/setup.py
apiverve_colorconverter/setup_dep.py
apiverve_colorconverter/tests/__init__.py
apiverve_colorconverter/tests/test_api.py
apiverve_colorconverter-1.1.8.dist-info/LICENSE
apiverve_colorconverter-1.1.8.dist-info/METADATA
apiverve_colorconverter-1.1.8.dist-info/WHEEL
apiverve_colorconverter-1.1.8.dist-info/top_level.txt
apiverve_colorconverter-1.1.8.dist-info/RECORD
